{
  "reportDate": "2026-07-03",
  "generatedAt": "2026-07-03T01:09:20Z",
  "title": "Günlük Ekonomik Takvim Raporu — 3 Temmuz 2026",
  "summary": "ABD Independence Day öncesi son işlem günü. Eurozone PMI verileri stagflasyon sinyali veriyor. Fear & Greed 34 (fear). 37 olay, 15 medium önem. ECB Lagarde ve BoE Bailey konuşmaları volatilite tetikleyici.",
  "events": [
    {
      "time": "All Day",
      "country": "",
      "importance": "holiday",
      "eventName": "United States - Independence Day",
      "actual": "",
      "forecast": "",
      "previous": "",
      "id": "evt_001",
      "countryFlag": "🏳️",
      "currency": "",
      "unit": "Index",
      "analysis": "ABD piyasaları yarın (4 Temmuz) Independence Day nedeniyle kapalı. Bugün erken saatlerde hacim düşüklüğü ve 'holiday squeeze' volatilitesi beklenebilir."
    },
    {
      "time": "00:00",
      "country": "KRW",
      "importance": "low",
      "eventName": "FX Reserves - USD (Jun)",
      "actual": "427.36B",
      "forecast": "",
      "previous": "426.99B",
      "id": "evt_002",
      "countryFlag": "🇰🇷",
      "currency": "KRW",
      "unit": "Billion USD",
      "analysis": "KRW FX rezervleri; piyasa için ikincil önem. Rezerv artışı = para birimi destek; düşüş = zayıflık sinyali."
    },
    {
      "time": "02:00",
      "country": "AUD",
      "importance": "low",
      "eventName": "S&P Global Manufacturing & Services PMI (Jun)",
      "actual": "50.40",
      "forecast": "49.80",
      "previous": "48.70",
      "id": "evt_003",
      "countryFlag": "🇦🇺",
      "currency": "AUD",
      "unit": "Index",
      "analysis": "AUD Composite PMI öncü gösterge; 50 üstü = expansion, altı = kontraksiyon."
    },
    {
      "time": "02:00",
      "country": "AUD",
      "importance": "low",
      "eventName": "S&P Global Services PMI (Jun)",
      "actual": "50.5",
      "forecast": "49.9",
      "previous": "48.7",
      "id": "evt_004",
      "countryFlag": "🇦🇺",
      "currency": "AUD",
      "unit": "Index",
      "analysis": "AUD S&P Global Services PMI (Jun) verisi; piyasa için sınırlı etki. Beklenen 49.9, önceki 48.7."
    },
    {
      "time": "03:30",
      "country": "JPY",
      "importance": "low",
      "eventName": "Manufacturing & Services PMI (Jun)",
      "actual": "52.80",
      "forecast": "52.50",
      "previous": "51.10",
      "id": "evt_005",
      "countryFlag": "🇯🇵",
      "currency": "JPY",
      "unit": "Index",
      "analysis": "JPY Composite PMI öncü gösterge; 50 üstü = expansion, altı = kontraksiyon."
    },
    {
      "time": "03:30",
      "country": "JPY",
      "importance": "medium",
      "eventName": "S&P Global Services PMI (Jun)",
      "actual": "52.2",
      "forecast": "51.8",
      "previous": "50.0",
      "id": "evt_006",
      "countryFlag": "🇯🇵",
      "currency": "JPY",
      "unit": "Index",
      "analysis": "Japonya Services PMI beklenen 51.8 (önceki 50.0). Japonya'da services expansion, ancak USD/JPY 160+ seviyelerinde BOJ intervention riski yüksek. Services PMI 52+ = JPY short squeeze riski (BOJ'un faiz artırım beklentilerini güçlendirir); 51 altı = JPY weakness devam. Nikkei 225 üzerinde 50 üstü = destek."
    },
    {
      "time": "40 min",
      "country": "CNY",
      "importance": "medium",
      "eventName": "RatingDog Services PMI (Jun)",
      "actual": "",
      "forecast": "53.0",
      "previous": "54.4",
      "id": "evt_007",
      "countryFlag": "🇨🇳",
      "currency": "CNY",
      "unit": "Index",
      "analysis": "Çin RatingDog Services PMI beklenen 53.0 (önceki 54.4). Çin'de services expansion devam ediyor ancak momentum yavaşlıyor. AUD/USD (Çin proxy) ve emtialar (demir cevheri, bakır) üzerinde etkili. 53.0 altı = AUD/USD 0.6350 test; 54+ = 0.6450. Hang Seng ve ASX 200 için kısa vadeli momentum sinyali."
    },
    {
      "time": "08:00",
      "country": "INR",
      "importance": "low",
      "eventName": "HSBC India Services PMI (Jun)",
      "actual": "",
      "forecast": "57.3",
      "previous": "57.3",
      "id": "evt_008",
      "countryFlag": "🇮🇳",
      "currency": "INR",
      "unit": "Index",
      "analysis": "INR HSBC India Services PMI (Jun) verisi; piyasa için sınırlı etki. Beklenen 57.3, önceki 57.3."
    },
    {
      "time": "08:00",
      "country": "INR",
      "importance": "low",
      "eventName": "HSBC Manufacturing & Services PMI (Jun)",
      "actual": "",
      "forecast": "57.40",
      "previous": "59.30",
      "id": "evt_009",
      "countryFlag": "🇮🇳",
      "currency": "INR",
      "unit": "Index",
      "analysis": "INR Composite PMI öncü gösterge; 50 üstü = expansion, altı = kontraksiyon."
    },
    {
      "time": "09:00",
      "country": "RUB",
      "importance": "medium",
      "eventName": "S&P Global Services PMI (Jun)",
      "actual": "",
      "forecast": "",
      "previous": "48.7",
      "id": "evt_010",
      "countryFlag": "🇷🇺",
      "currency": "RUB",
      "unit": "Index",
      "analysis": "Rusya Services PMI beklenen — (önceki 48.7). Rusya'da services kontraksiyonu devam ediyor, ancak petrol fiyatları (Brent ~$75) ve ruble stabilitesi öncelikli. Bu veri EM piyasaları ve özellikle MOEX üzerinde sınırlı etki. USD/RUB 85+ seviyeleri = RUB weakness."
    },
    {
      "time": "09:45",
      "country": "EUR",
      "importance": "low",
      "eventName": "French Industrial Production (MoM) (May)",
      "actual": "",
      "forecast": "-0.3%",
      "previous": "0.1%",
      "id": "evt_011",
      "countryFlag": "🇪🇺",
      "currency": "EUR",
      "unit": "Index",
      "analysis": "Sanayi üretimi; üretim sektörü aktivitesini yansıtır. Beklenen -0.3%, önceki 0.1%."
    },
    {
      "time": "10:00",
      "country": "EUR",
      "importance": "low",
      "eventName": "Spanish Industrial Production (YoY) (May)",
      "actual": "",
      "forecast": "",
      "previous": "2.0%",
      "id": "evt_012",
      "countryFlag": "🇪🇺",
      "currency": "EUR",
      "unit": "Index",
      "analysis": "Sanayi üretimi; üretim sektörü aktivitesini yansıtır. Beklenen , önceki 2.0%."
    },
    {
      "time": "10:15",
      "country": "EUR",
      "importance": "medium",
      "eventName": "HCOB Spain Services PMI (Jun)",
      "actual": "",
      "forecast": "51.0",
      "previous": "50.1",
      "id": "evt_013",
      "countryFlag": "🇪🇺",
      "currency": "EUR",
      "unit": "Index",
      "analysis": "İspanya Services PMI beklenen 51.0 (önceki 50.1). İspanya Eurozone içinde nispeten güçlü. 51+ = IBEX 35 destek; özellikle turizm ve hizmet hisseleri (ITX, AENA) pozitif etkilenebilir. Eurozone'un güçlü halkası olarak İspanya verisi EUR/USD'de 20-30 pip destek sağlayabilir."
    },
    {
      "time": "10:15",
      "country": "ZAR",
      "importance": "low",
      "eventName": "S&P Global Manufacturing PMI (Jun)",
      "actual": "",
      "forecast": "",
      "previous": "49.6",
      "id": "evt_014",
      "countryFlag": "🇿🇦",
      "currency": "ZAR",
      "unit": "Index",
      "analysis": "ZAR S&P Global Manufacturing PMI (Jun) verisi; piyasa için sınırlı etki. Beklenen , önceki 49.6."
    },
    {
      "time": "10:45",
      "country": "EUR",
      "importance": "low",
      "eventName": "HCOB Italy Composite PMI (Jun)",
      "actual": "",
      "forecast": "",
      "previous": "50.4",
      "id": "evt_015",
      "countryFlag": "🇪🇺",
      "currency": "EUR",
      "unit": "Index",
      "analysis": "EUR HCOB Italy Composite PMI (Jun) verisi; piyasa için sınırlı etki. Beklenen , önceki 50.4."
    },
    {
      "time": "10:45",
      "country": "EUR",
      "importance": "medium",
      "eventName": "HCOB Italy Services PMI (Jun)",
      "actual": "",
      "forecast": "50.3",
      "previous": "49.4",
      "id": "evt_016",
      "countryFlag": "🇪🇺",
      "currency": "EUR",
      "unit": "Index",
      "analysis": "İtalya Services PMI beklenen 50.3 (önceki 49.4). İtalya'da hafif bir expansion sinyali, ancak Eurozone genelindeki zayıflık bu veriyi gölgeleyebilir. FTSE MIB üzerinde 50 altı = İtalyan bankacılık hisseleri (UNI.MI, ISP.MI) baskı; 50.5+ = recovery play."
    },
    {
      "time": "10:50",
      "country": "EUR",
      "importance": "low",
      "eventName": "HCOB France Composite PMI (Jun)",
      "actual": "",
      "forecast": "47.6",
      "previous": "44.9",
      "id": "evt_017",
      "countryFlag": "🇪🇺",
      "currency": "EUR",
      "unit": "Index",
      "analysis": "EUR HCOB France Composite PMI (Jun) verisi; piyasa için sınırlı etki. Beklenen 47.6, önceki 44.9."
    },
    {
      "time": "10:50",
      "country": "EUR",
      "importance": "medium",
      "eventName": "HCOB France Services PMI (Jun)",
      "actual": "",
      "forecast": "47.4",
      "previous": "47.4",
      "id": "evt_018",
      "countryFlag": "🇪🇺",
      "currency": "EUR",
      "unit": "Index",
      "analysis": "Fransa Services PMI beklenen 47.4 (önceki 47.4). Fransa'da siyasi belirsizlik (hükümet istikrarsızlığı) + services zayıflığı CAC 40 üzerinde çift baskı. 47.4 altı = CAC 40 gap down; 48+ = mean reversion bounce. EUR/USD üzerinde Fransa verisi genellikle Almanya verisinden daha az etkili."
    },
    {
      "time": "10:55",
      "country": "EUR",
      "importance": "low",
      "eventName": "HCOB Germany Composite PMI (Jun)",
      "actual": "",
      "forecast": "48.0",
      "previous": "48.8",
      "id": "evt_019",
      "countryFlag": "🇪🇺",
      "currency": "EUR",
      "unit": "Index",
      "analysis": "EUR HCOB Germany Composite PMI (Jun) verisi; piyasa için sınırlı etki. Beklenen 48.0, önceki 48.8."
    },
    {
      "time": "10:55",
      "country": "EUR",
      "importance": "medium",
      "eventName": "HCOB Germany Services PMI (Jun)",
      "actual": "",
      "forecast": "46.8",
      "previous": "48.1",
      "id": "evt_020",
      "countryFlag": "🇪🇺",
      "currency": "EUR",
      "unit": "Index",
      "analysis": "Almanya Services PMI beklenen 46.8 (önceki 48.1) — ciddi bir yavaşlama. Almanya, Eurozone'in lokomotifi; services kontraksiyonu DAX ve EUR/USD üzerinde baskı yaratır. 46.8'e yakın veya altı = EUR/USD 30-50 pip düşüş; 48+ = short covering. German Buba President Nagel aynı gün konuşacak, bu veri + Nagel kombinasyonu DAX'ta 200+ pip range potansiyeli."
    },
    {
      "time": "11:00",
      "country": "EUR",
      "importance": "low",
      "eventName": "Italian Retail Sales (MoM) (May)",
      "actual": "",
      "forecast": "0.2%",
      "previous": "0.0%",
      "id": "evt_021",
      "countryFlag": "🇪🇺",
      "currency": "EUR",
      "unit": "Index",
      "analysis": "Perakende satışlar; tüketici harcamaları ve iç talep göstergesi."
    },
    {
      "time": "11:00",
      "country": "EUR",
      "importance": "low",
      "eventName": "Italian Retail Sales (YoY) (May)",
      "actual": "",
      "forecast": "",
      "previous": "1.6%",
      "id": "evt_022",
      "countryFlag": "🇪🇺",
      "currency": "EUR",
      "unit": "Index",
      "analysis": "Perakende satışlar; tüketici harcamaları ve iç talep göstergesi."
    },
    {
      "time": "11:00",
      "country": "EUR",
      "importance": "medium",
      "eventName": "ECB President Lagarde Speaks",
      "actual": "",
      "forecast": "",
      "previous": "",
      "id": "evt_023",
      "countryFlag": "🇪🇺",
      "currency": "EUR",
      "unit": "Index",
      "analysis": "ECB Başkanı Lagarde, Aix-en-Provence Ekonomi Forumu'nda 'Belirsizlik Çağında Yön Bulmak' panelinde konuşacak. Önceki PMI verileri (Eurozone Composite 49.5, Services 48.9) stagflasyon sinyali veriyor. Lagarde'nin services inflation vurgusu ve 'data-dependent' mesajları EUR/USD ve DAX futures üzerinde anlık volatilite yaratır. Hawkish ton = EUR/USD long squeeze; dovish ton = EUR/USD gap fade fırsatı."
    },
    {
      "time": "11:00",
      "country": "EUR",
      "importance": "medium",
      "eventName": "HCOB Eurozone Composite PMI (Jun)",
      "actual": "",
      "forecast": "49.5",
      "previous": "49.5",
      "id": "evt_024",
      "countryFlag": "🇪🇺",
      "currency": "EUR",
      "unit": "Index",
      "analysis": "Eurozone Composite PMI beklenen 49.5 (önceki 49.5). 50 altı = kontraksiyon. Hizmet sektöründeki zayıflık (Services PMI 48.9) ve üretimdeki durgunluk birleşince Eurozone GDP Q2 negatif bölgeye kayabilir. EUR/USD'de 1.1350–1.1450 range-bound kalabilir. DAX ve FTSE MIB'de PMI'dan better-than-expected çıkış = 0.5–1.0% momentum rally."
    },
    {
      "time": "11:00",
      "country": "EUR",
      "importance": "medium",
      "eventName": "HCOB Eurozone Services PMI (Jun)",
      "actual": "",
      "forecast": "48.9",
      "previous": "48.9",
      "id": "evt_025",
      "countryFlag": "🇪🇺",
      "currency": "EUR",
      "unit": "Index",
      "analysis": "Eurozone Services PMI beklenen 48.9 (önceki 48.9). Services enflasyonu ECB'nin en hassas noktası. Hizmet sektöründe fiyat baskısı sürdükçe ECB rate cut beklentileri ertelenir. Bu veri EUR/USD ve Eurozone bond yields (Bund) üzerinde etkili. 48.9 altı = EUR/USD fade toward 1.1300; 49.5 üstü = 1.1500 test."
    },
    {
      "time": "11:30",
      "country": "GBP",
      "importance": "medium",
      "eventName": "S&P Global Composite PMI (Jun)",
      "actual": "",
      "forecast": "49.4",
      "previous": "49.7",
      "id": "evt_026",
      "countryFlag": "🇬🇧",
      "currency": "GBP",
      "unit": "Index",
      "analysis": "UK Composite PMI beklenen 49.4 (önceki 49.7). 50 altı = ekonomik daralma. BoE'nin 4.50% rate hold'u bu veri ile birleşince August'ta cut beklentisi güçlenir. GBP/USD'de 49.4 altı = dovish BoE pricing = GBP weakness; 50+ = short covering. UK gilt yields 2y < 4.0% = dovish signal."
    },
    {
      "time": "11:30",
      "country": "GBP",
      "importance": "medium",
      "eventName": "S&P Global Services PMI (Jun)",
      "actual": "",
      "forecast": "48.7",
      "previous": "49.3",
      "id": "evt_027",
      "countryFlag": "🇬🇧",
      "currency": "GBP",
      "unit": "Index",
      "analysis": "UK Services PMI beklenen 48.7 (önceki 49.3). BoE Başkanı Bailey aynı gün 18:00'de konuşacak. Services PMI 48.7 = kontraksiyon; BoE'nin August rate cut sinyali verme olasılığını artırır. GBP/USD 1.3300–1.3400 range'de; 48.7 altı = 1.3250 test; 49.5+ = 1.3450. GBP/EUR cross'ta 1.1450–1.1650 bandı korunur."
    },
    {
      "time": "12:00",
      "country": "RUB",
      "importance": "low",
      "eventName": "Russian Forex Intervention (Jul)",
      "actual": "",
      "forecast": "",
      "previous": "208.2B",
      "id": "evt_028",
      "countryFlag": "🇷🇺",
      "currency": "RUB",
      "unit": "Billion USD",
      "analysis": "Rusya MB döviz müdahalesi; ruble stabilitesi ve rezerv yönetimi göstergesi."
    },
    {
      "time": "13:00",
      "country": "EUR",
      "importance": "low",
      "eventName": "German Car Registration (YoY) (Jun)",
      "actual": "",
      "forecast": "",
      "previous": "0.1%",
      "id": "evt_029",
      "countryFlag": "🇪🇺",
      "currency": "EUR",
      "unit": "Index",
      "analysis": "Otomobil satışları; dayanıklı tüketim malları ve sanayi üretiminin öncü göstergesi."
    },
    {
      "time": "13:00",
      "country": "EUR",
      "importance": "low",
      "eventName": "Spanish Consumer Confidence (May)",
      "actual": "",
      "forecast": "",
      "previous": "77.7",
      "id": "evt_030",
      "countryFlag": "🇪🇺",
      "currency": "EUR",
      "unit": "Index",
      "analysis": "Tüketici güveni; gelecek dönem harcama eğilimini gösterir."
    },
    {
      "time": "14:30",
      "country": "INR",
      "importance": "low",
      "eventName": "FX Reserves, USD",
      "actual": "",
      "forecast": "",
      "previous": "672.59B",
      "id": "evt_031",
      "countryFlag": "🇮🇳",
      "currency": "INR",
      "unit": "Billion USD",
      "analysis": "INR FX rezervleri; piyasa için ikincil önem. Rezerv artışı = para birimi destek; düşüş = zayıflık sinyali."
    },
    {
      "time": "15:00",
      "country": "BRL",
      "importance": "medium",
      "eventName": "Industrial Production (YoY) (May)",
      "actual": "",
      "forecast": "1.3%",
      "previous": "2.7%",
      "id": "evt_032",
      "countryFlag": "🇧🇷",
      "currency": "BRL",
      "unit": "Index",
      "analysis": "Brezilya Industrial Production (YoY) beklenen 1.3% (önceki 2.7%). Yavaşlama sinyali; BRL üzerinde baskı. USD/BRL 5.60+ = BRL weakness; 1.3% altı = 5.70 test. Bovespa üzerinde sanayi hisseleri (VALE, PBR) baskı. EM risk-off ortamında BRL genellikle ilk satılan para birimlerinden."
    },
    {
      "time": "15:00",
      "country": "BRL",
      "importance": "low",
      "eventName": "Industrial Production (MoM) (May)",
      "actual": "",
      "forecast": "0.3%",
      "previous": "0.7%",
      "id": "evt_033",
      "countryFlag": "🇧🇷",
      "currency": "BRL",
      "unit": "Index",
      "analysis": "Sanayi üretimi; üretim sektörü aktivitesini yansıtır. Beklenen 0.3%, önceki 0.7%."
    },
    {
      "time": "16:00",
      "country": "BRL",
      "importance": "low",
      "eventName": "S&P Global Composite PMI (Jun)",
      "actual": "",
      "forecast": "",
      "previous": "49.5",
      "id": "evt_034",
      "countryFlag": "🇧🇷",
      "currency": "BRL",
      "unit": "Index",
      "analysis": "BRL Composite PMI; özel sektör aktivitesinin genel görünümü."
    },
    {
      "time": "16:00",
      "country": "BRL",
      "importance": "low",
      "eventName": "S&P Global Services PMI (Jun)",
      "actual": "",
      "forecast": "",
      "previous": "50.4",
      "id": "evt_035",
      "countryFlag": "🇧🇷",
      "currency": "BRL",
      "unit": "Index",
      "analysis": "BRL S&P Global Services PMI (Jun) verisi; piyasa için sınırlı etki. Beklenen , önceki 50.4."
    },
    {
      "time": "18:00",
      "country": "GBP",
      "importance": "medium",
      "eventName": "BoE Gov Bailey Speaks",
      "actual": "",
      "forecast": "",
      "previous": "",
      "id": "evt_036",
      "countryFlag": "🇬🇧",
      "currency": "GBP",
      "unit": "Index",
      "analysis": "BoE Başkanı Bailey, Aix-en-Provence Forumu'nda konuşacak. UK Services PMI 48.7 (kontraksiyon) öncesi/sonrası bu konuşma kritik. Bailey'nin 'data-dependent' ve services inflation vurgusu GBP/USD üzerinde 50-80 pip volatilite yaratır. Dovish sinyal (August cut) = GBP/USD 1.3200 test; hawkish hold = 1.3450."
    },
    {
      "time": "18:00",
      "country": "EUR",
      "importance": "medium",
      "eventName": "German Buba President Nagel Speaks",
      "actual": "",
      "forecast": "",
      "previous": "",
      "id": "evt_037",
      "countryFlag": "🇪🇺",
      "currency": "EUR",
      "unit": "Index",
      "analysis": "Bundesbank Başkanı Nagel, Aix-en-Provence Forumu'nda 'Fiscal & Monetary Policy: Is the Line Starting to Blur?' panelinde konuşacak. Almanya Services PMI 46.8 (ciddi zayıflama) + Nagel konuşması = DAX ve EUR/USD üzerinde çift volatilite. Hawkish Nagel = EUR/USD short squeeze; dovish/fiscal stimulus vurgusu = DAX rally."
    }
  ],
  "optionSetups": [
    {
      "asset": "EUR/USD",
      "bias": "Short",
      "trigger": "HCOB Eurozone PMI < 49.0",
      "invalidation": "PMI > 50.0 + Lagarde hawkish",
      "setupType": "0DTE PUT / Weekly PUT",
      "rationale": "Stagflasyon + ECB dovish pricing = EUR fade. 1.1350 target."
    },
    {
      "asset": "DAX",
      "bias": "Long",
      "trigger": "Germany Services PMI > 48.0 + Nagel fiscal vurgusu",
      "invalidation": "PMI < 46.0 + Lagarde hawkish",
      "setupType": "Weekly CALL / Bull Spread",
      "rationale": "Fiscal stimulus expectation + oversold bounce. 21,500 target."
    },
    {
      "asset": "GBP/USD",
      "bias": "Short",
      "trigger": "UK Services PMI < 48.5 + Bailey dovish",
      "invalidation": "PMI > 50.0 + Bailey hawkish",
      "setupType": "0DTE PUT / Weekly PUT",
      "rationale": "BoE August cut pricing + recession signal. 1.3250 target."
    },
    {
      "asset": "SPY",
      "bias": "Long",
      "trigger": "VWAP bounce + VIX crush",
      "invalidation": "Break below 740",
      "setupType": "0DTE CALL / Short Put Spread",
      "rationale": "Holiday squeeze + oversold tech. 750 target."
    },
    {
      "asset": "QQQ",
      "bias": "Short",
      "trigger": "Tech selloff continuation",
      "invalidation": "720 reclaim",
      "setupType": "Weekly PUT / Bear Spread",
      "rationale": "AI overcapacity narrative + rotation. 700 target."
    }
  ],
  "vixOutlook": "Independence Day öncesi VIX crush beklentisi yüksek. VIX 16-18 bandında; 0DTE gamma exposure düşük. PMI volatilitesi geçici VIX spike yaratabilir ama kapanışta crush eğilimi.",
  "fearGreedOutlook": "Fear & Greed Index 34 (fear). Piyasa 'fear' bölgesinde ama extreme fear değil. Tech selloff + Eurozone zayıflığı + Independence Day öncesi hacim düşüklüğü = mixed sentiment. Contrarian long fırsatı olabilir.",
  "marketNarrative": "Independence Day öncesi son işlem gününde piyasa 'holiday squeeze' + 'risk-off' havası arasında gidip geliyor. Eurozone PMI verileri stagflasyonu doğruluyor. ECB Lagarde ve BoE Bailey konuşmaları Avrupa seansında volatilite tetikleyici. Tech selloff (QQQ -3.11%) rotation devam ediyor. DXY güçlü. 0DTE'lerde dikkatli olunmalı; weekly spread'ler tercih edilebilir."
}